autodistill_rekognition/__init__.py
autodistill_rekognition/rekognition_model.py
autodistill_rekognition-0.1.0.dist-info/LICENSE
autodistill_rekognition-0.1.0.dist-info/METADATA
autodistill_rekognition-0.1.0.dist-info/WHEEL
autodistill_rekognition-0.1.0.dist-info/top_level.txt
autodistill_rekognition-0.1.0.dist-info/RECORD
